alibabacloud_green20220302/__init__.py
alibabacloud_green20220302/client.py
alibabacloud_green20220302/models/__init__.py
alibabacloud_green20220302/models/_describe_file_moderation_result_request.py
alibabacloud_green20220302/models/_describe_file_moderation_result_response.py
alibabacloud_green20220302/models/_describe_file_moderation_result_response_body.py
alibabacloud_green20220302/models/_describe_image_moderation_result_request.py
alibabacloud_green20220302/models/_describe_image_moderation_result_response.py
alibabacloud_green20220302/models/_describe_image_moderation_result_response_body.py
alibabacloud_green20220302/models/_describe_image_result_ext_request.py
alibabacloud_green20220302/models/_describe_image_result_ext_response.py
alibabacloud_green20220302/models/_describe_image_result_ext_response_body.py
alibabacloud_green20220302/models/_describe_multimodal_moderation_result_request.py
alibabacloud_green20220302/models/_describe_multimodal_moderation_result_response.py
alibabacloud_green20220302/models/_describe_multimodal_moderation_result_response_body.py
alibabacloud_green20220302/models/_describe_upload_token_response.py
alibabacloud_green20220302/models/_describe_upload_token_response_body.py
alibabacloud_green20220302/models/_describe_url_moderation_result_request.py
alibabacloud_green20220302/models/_describe_url_moderation_result_response.py
alibabacloud_green20220302/models/_describe_url_moderation_result_response_body.py
alibabacloud_green20220302/models/_file_moderation_request.py
alibabacloud_green20220302/models/_file_moderation_response.py
alibabacloud_green20220302/models/_file_moderation_response_body.py
alibabacloud_green20220302/models/_image_async_moderation_request.py
alibabacloud_green20220302/models/_image_async_moderation_response.py
alibabacloud_green20220302/models/_image_async_moderation_response_body.py
alibabacloud_green20220302/models/_image_batch_moderation_request.py
alibabacloud_green20220302-3.2.1.dist-info/LICENSE
alibabacloud_green20220302-3.2.1.dist-info/METADATA
alibabacloud_green20220302-3.2.1.dist-info/WHEEL
alibabacloud_green20220302-3.2.1.dist-info/top_level.txt
alibabacloud_green20220302-3.2.1.dist-info/RECORD
